physical_design/my_design_synth.v
module my_design_synth (
    input wire clk,
    input wire rst,
    output reg [7:0] out_signal
);

always @(posedge clk or posedge rst) begin
    if (rst)
        out_signal <= 8'b10101010; // Start with alternate bits
    else
        out_signal <= ~out_signal; // Toggle bits every cycle
end

endmodule

physical_design/netlist_tb.v
`timescale 1ns/1ps  // Define time units and precision

module my_design_tb;
  reg clk, rst;
  wire [7:0] out_signal;

  // Instantiate synthesized netlist
  my_design_synth dut (
    .clk(clk),
    .rst(rst),
    .out_signal(out_signal)
  );

  // Clock Generation (10ns period, 5ns high, 5ns low)
  always #5 clk = ~clk;

  initial begin
    // Initialize signals before starting simulation
    clk = 0;
    rst = 1;

    // Dump waveform data
    $dumpfile("netlist_verification.vcd");
    $dumpvars(0, dut); // Dumps only the DUT variables

    // Reset sequence
    #20 rst = 0; // Hold reset high for 20ns
    
    // Run for 100ns after reset
    #100 $finish;
  end
endmodule

physical_design/netlist_verification.vcd
$date
	Wed Feb 26 08:59:10 2025
$end
$version
	Icarus Verilog
$end
$timescale
	1ps
$end
$scope module my_design_tb $end
$scope module dut $end
$var wire 1 ! clk $end
$var wire 1 " rst $end
$var reg 8 # out_signal [7:0] $end
$upscope $end
$upscope $end
$enddefinitions $end
$comment Show the parameter values. $end
$dumpall
$end
#0
$dumpvars
b10101010 #
1"
0!
$end
#5000
1!
#10000
0!
#15000
1!
#20000
0!
0"
#25000
b1010101 #
1!
#30000
0!
#35000
b10101010 #
1!
#40000
0!
#45000
b1010101 #
1!
#50000
0!
#55000
b10101010 #
1!
#60000
0!
#65000
b1010101 #
1!
#70000
0!
#75000
b10101010 #
1!
#80000
0!
#85000
b1010101 #
1!
#90000
0!
#95000
b10101010 #
1!
#100000
0!
#105000
b1010101 #
1!
#110000
0!
#115000
b10101010 #
1!
